{
  "links": [
    "fffalfa.net"
  ],
  "proxies": [],
  "pixKeys": [],
  "extensions": [],
  "settings": {
    "delay": 5,
    "openings": 2,
    "toggles": {
      "proxy-mode-list": false,
      "proxy-mode-rotating": false,
      "proxy-mode-none": true,
      "default-resolution-checkbox": true,
      "random-passwords-toggle": false,
      "mute-audio-toggle": false,
      "delay-toggle": false
    },
    "lastSaved": "2025-09-02T04:56:37.036Z"
  },
  "automation": {
    "muteAudio": false,
    "depositMin": 0,
    "depositMax": 0,
    "delayEnabled": false,
    "delaySeconds": 5,
    "password": "",
    "withdrawPassword": "",
    "randomPasswords": false
  }
}